[{"boundingBox": [119, 44, 166, 44, 166, 60, 119, 60], "text": "El Valle "}, {"boundingBox": [93, 58, 181, 58, 181, 89, 93, 89], "text": "Mexican Restaurant 305 W. John St. "}, {"boundingBox": [93, 86, 181, 86, 181, 116, 93, 116], "text": "Matthews, NC 28105 (704) 845-1417 "}, {"boundingBox": [34, 125, 251, 125, 251, 145, 34, 145], "text": "Server : GEOVANNY Station: 10 "}, {"boundingBox": [34, 152, 250, 152, 250, 171, 34, 171], "text": "Order #: 403593 Dine In "}, {"boundingBox": [35, 165, 247, 165, 247, 184, 35, 184], "text": "Table: 9 Guests: 1 "}, {"boundingBox": [34, 191, 246, 191, 246, 210, 34, 210], "text": "1 GUACAMOLE DIP 3.99 "}, {"boundingBox": [34, 204, 248, 204, 248, 222, 34, 222], "text": "1 DIET COKE 2 . 15 "}, {"boundingBox": [34, 217, 247, 217, 247, 235, 34, 235], "text": "1 LUNCH FAJITAS 17.75 "}, {"boundingBox": [36, 228, 245, 228, 245, 249, 36, 249], "text": "1 TORTILLAS (3) 1.25 "}, {"boundingBox": [38, 241, 245, 241, 245, 260, 38, 260], "text": "1 SOUR CREAM 1.25 "}, {"boundingBox": [32, 266, 245, 266, 245, 284, 32, 284], "text": "SUB TOTAL : 16.39 "}, {"boundingBox": [29, 279, 246, 279, 246, 296, 29, 296], "text": "Tax 1: 1.36 "}, {"boundingBox": [24, 306, 248, 306, 248, 336, 24, 336], "text": "TOTAL $17.75 "}, {"boundingBox": [75, 344, 174, 344, 174, 373, 75, 373], "text": ">> Ticket #: 7 < "}, {"boundingBox": [65, 367, 154, 367, 154, 402, 65, 402], "text": "12/2/2017 11:48:28 AM THANK YOU! "}]