[{"boundingBox": [197, 100, 467, 100, 467, 177, 197, 177], "text": "Don Juan Mexican Restaurant 124 East Park Ave "}, {"boundingBox": [248, 180, 453, 180, 453, 239, 248, 239], "text": "Long Beach, NY 11561 (516) 442-4944 "}, {"boundingBox": [131, 272, 611, 272, 611, 299, 131, 299], "text": "Server : Regina Station: 4 "}, {"boundingBox": [133, 332, 606, 332, 606, 358, 133, 358], "text": "Order #: 28731 Dine In "}, {"boundingBox": [136, 361, 606, 361, 606, 387, 136, 387], "text": "Table: 1 Guests: 2 "}, {"boundingBox": [138, 417, 601, 417, 601, 443, 138, 443], "text": "2 Red Sangria Glass 14,00 "}, {"boundingBox": [139, 446, 602, 446, 602, 474, 139, 474], "text": "1 #4-COMBO FAJITAS 22.95 "}, {"boundingBox": [161, 474, 245, 474, 245, 529, 161, 529], "text": "Flour Tortilla Chicken "}, {"boundingBox": [161, 532, 220, 532, 220, 583, 161, 583], "text": "Shrimp Steak "}, {"boundingBox": [140, 587, 600, 587, 600, 616, 140, 616], "text": "1 #34-BURRITO SUPREME 14.95 "}, {"boundingBox": [159, 617, 244, 617, 244, 640, 159, 640], "text": "w/ Beef "}, {"boundingBox": [136, 672, 598, 672, 598, 701, 136, 701], "text": "Bar Subtotal: 14.00 "}, {"boundingBox": [138, 698, 599, 698, 599, 731, 138, 731], "text": "Food Subtotal : 37.90 "}, {"boundingBox": [135, 727, 601, 727, 601, 762, 135, 762], "text": "NY State : 4.48 "}, {"boundingBox": [139, 786, 598, 786, 598, 840, 139, 840], "text": "TOTAL: $56.38 "}, {"boundingBox": [257, 863, 473, 863, 473, 914, 257, 914], "text": "> > Ticket #: 23 < "}, {"boundingBox": [249, 907, 656, 907, 656, 918, 249, 918], "text": "11/6/2013 8:14:53 PM Gracias "}, {"boundingBox": [306, 970, 639, 970, 639, 989, 306, 989], "text": "THANK YOU! C "}]